MANIFEST.in
README.md
setup.py
PyCorder/__init__.py
PyCorder/manager.py
PyCorder/record.py
PyCorder.egg-info/PKG-INFO
PyCorder.egg-info/SOURCES.txt
PyCorder.egg-info/dependency_links.txt
PyCorder.egg-info/top_level.txt