Metadata-Version: 2.1
Name: PyCorder
Version: 1.0.1
Summary: A audio recorder for python.
Author: LUA9
Maintainer: LUA9
License: UNKNOWN
Platform: UNKNOWN
Requires: pipwin
